dsxt/__init__.py
dsxt/threshold.py
dsxt-0.0.3.dist-info/WHEEL
dsxt-0.0.3.dist-info/METADATA
dsxt-0.0.3.dist-info/RECORD
