Metadata-Version: 2.1
Name: dsxt
Version: 0.0.3
Summary: Data Science Extensions
Author: tripl3a
Author-email: 34123487+tripl3a@users.noreply.github.com
Requires-Python: >=3.9,<4.0
Classifier: Programming Language :: Python :: 3
Classifier: Programming Language :: Python :: 3.9
Requires-Dist: numpy (>=1.20,<2.0)
Requires-Dist: pandas (>=1.2,<2.0)
Requires-Dist: scikit-learn (==0.24.2)
